AOS/__init__.py
AOS/__main__.py
AOS/color_detection.py
AOS/database.py
AOS/helpers.py
AOS/middleware.py
AOS/deps/il/.gitignore
AOS/deps/il/LICENSE.txt
AOS/deps/il/README.md
AOS/deps/il/__init__.py
AOS/deps/il/pyproject.toml
AOS/installer/example_unit.service
AOS/models/RatingPayload.py
AOS/reports/report.py
AOS/routes/backend.py
AOS/routes/frontend.py
AOS/routes/public.py
AOS/utils/logging.py
AOS/utils/release_bot.py
AOS/utils/usage_graph.py
adm_aos-4.5.1.dist-info/METADATA
adm_aos-4.5.1.dist-info/WHEEL
adm_aos-4.5.1.dist-info/entry_points.txt
adm_aos-4.5.1.dist-info/licenses/LICENSE
adm_aos-4.5.1.dist-info/RECORD
