Metadata-Version: 2.4
Name: adm-aos
Version: 4.5.1
Summary: Administer's AOS service for distributing apps.
Project-URL: homepage, https://admsoftware.org
Author-email: pyxfluff <business@notpyx.me>
License-File: LICENSE
Requires-Python: >=3.11
Requires-Dist: colorthief
Requires-Dist: fastapi
Requires-Dist: flake8>=7.2.0
Requires-Dist: httpx
Requires-Dist: levenshtein
Requires-Dist: matplotlib
Requires-Dist: nanoid
Requires-Dist: orjson
Requires-Dist: pathlib
Requires-Dist: psutil>=7.0.0
Requires-Dist: pymongo
Requires-Dist: uvicorn
